lvlspy/__about__.py
lvlspy/__init__.py
lvlspy/level.py
lvlspy/properties.py
lvlspy/spcoll.py
lvlspy/species.py
lvlspy/transition.py
lvlspy/calculate/__init__.py
lvlspy/calculate/evolve/__init__.py
lvlspy/calculate/evolve/_evolve.py
lvlspy/calculate/isomer/__init__.py
lvlspy/calculate/isomer/_isomer.py
lvlspy/calculate/weisskopf/__init__.py
lvlspy/calculate/weisskopf/_weisskopf.py
lvlspy/io/__init__.py
lvlspy/io/ensdf/__init__.py
lvlspy/io/ensdf/_ensdf.py
lvlspy/io/xml/__init__.py
lvlspy/io/xml/_xml.py
lvlspy/io/xml/xsd_pub/catalog
lvlspy/io/xml/xsd_pub/level_types.xsd
lvlspy/io/xml/xsd_pub/levels.xsd
lvlspy/io/xml/xsd_pub/liblvls_input.xsd
lvlspy/io/xml/xsd_pub/spcoll.xsd
lvlspy/io/xml/xsd_pub/zone_types.xsd
lvlspy/io/xml/xsd_pub/zones.xsd
lvlspy-4.0.0.dist-info/licenses/LICENSE
lvlspy-4.0.0.dist-info/METADATA
lvlspy-4.0.0.dist-info/WHEEL
lvlspy-4.0.0.dist-info/top_level.txt
lvlspy-4.0.0.dist-info/RECORD
