Metadata-Version: 2.4
Name: lvlspy
Version: 4.0.0
Summary: Python project to work with quantum level system data
Home-page: https://github.com/jaadt7/lvlspy
Author: Clemson University
Author-email: jtannou@g.clemson.edu
License: GPLv3+
Project-URL: Bug Reports, https://github.com/jaadt7/lvlspy/issues
Project-URL: Source, https://github.com/jaadt7/lvlspy/
Keywords: astronomy nuclear astrophysics
Classifier: Development Status :: 5 - Production/Stable
Classifier: Intended Audience :: Science/Research
Classifier: Topic :: Scientific/Engineering :: Astronomy
Classifier: License :: OSI Approved :: GNU General Public License v3 or later (GPLv3+)
Classifier: Programming Language :: Python :: 2
Classifier: Programming Language :: Python :: 2.7
Classifier: Programming Language :: Python :: 3
Classifier: Programming Language :: Python :: 3.4
Classifier: Programming Language :: Python :: 3.5
Classifier: Programming Language :: Python :: 3.6
Classifier: Programming Language :: Python :: 3.7
License-File: LICENSE
Requires-Dist: lxml
Requires-Dist: numpy
Requires-Dist: gslconsts
Provides-Extra: dev
Requires-Dist: check-manifest; extra == "dev"
Provides-Extra: test
Requires-Dist: coverage; extra == "test"
Dynamic: author
Dynamic: author-email
Dynamic: classifier
Dynamic: description
Dynamic: description-content-type
Dynamic: home-page
Dynamic: keywords
Dynamic: license
Dynamic: license-file
Dynamic: project-url
Dynamic: provides-extra
Dynamic: requires-dist
Dynamic: summary
